pyrulelearn/__init__.py
pyrulelearn/cplex_wrap.py
pyrulelearn/imli.py
pyrulelearn/maxsat_wrap.py
pyrulelearn/utils.py
pyrulelearn-1.1.1.dist-info/LICENSE
pyrulelearn-1.1.1.dist-info/METADATA
pyrulelearn-1.1.1.dist-info/WHEEL
pyrulelearn-1.1.1.dist-info/top_level.txt
pyrulelearn-1.1.1.dist-info/RECORD
