Metadata-Version: 2.1
Name: pyrulelearn
Version: 1.1.1
Summary: This library can be used to generate interpretable classification rules expressed as CNF/DNF and relaxed-CNF
Home-page: https://github.com/meelgroup/MLIC
Download-URL: https://github.com/meelgroup/MLIC/archive/v1.1.1.tar.gz
Author: Bishwamittra Ghosh
Author-email: bishwamittra.ghosh@gmail.com
License: MIT
Keywords: Classification Rules,Interpretable Rules,CNF Classification Rules,DNF Classification Rules,MaxSAT-based Rule Learning
Platform: UNKNOWN
Classifier: Development Status :: 3 - Alpha
Classifier: Intended Audience :: Developers
Classifier: Topic :: Software Development :: Build Tools
Classifier: License :: OSI Approved :: MIT License
Classifier: Programming Language :: Python :: 3
Classifier: Programming Language :: Python :: 3.4
Classifier: Programming Language :: Python :: 3.5
Classifier: Programming Language :: Python :: 3.6
License-File: LICENSE
